django_mjml_email/__init__.py
django_mjml_email/backend.py
django_mjml_email/mjml_email.py
django_mjml_email-0.1.0.dist-info/licenses/LICENSE
django_mjml_email-0.1.0.dist-info/WHEEL
django_mjml_email-0.1.0.dist-info/METADATA
django_mjml_email-0.1.0.dist-info/RECORD
